discer/__init__.py
discer/grouping.py
discer/ordering.py
discer/relations.py
discer-0.1.1.dist-info/LICENSE
discer-0.1.1.dist-info/METADATA
discer-0.1.1.dist-info/WHEEL
discer-0.1.1.dist-info/top_level.txt
discer-0.1.1.dist-info/RECORD
