Metadata-Version: 2.1
Name: discer
Version: 0.1.1
Summary: Generic linear-time sorting
Author-email: Brendan <brendandeleeuw@gmail.com>
License: MIT License
Project-URL: Homepage, https://github.com/MystiriodisLykos/discer/tree/v0.1.1
Classifier: Programming Language :: Python
Classifier: Programming Language :: Python :: 3
Requires-Python: >=3.10
License-File: LICENSE
